mcp_server_sqlite3.py
mcp_server_sqlite3-20260116.dist-info/METADATA
mcp_server_sqlite3-20260116.dist-info/WHEEL
mcp_server_sqlite3-20260116.dist-info/entry_points.txt
mcp_server_sqlite3-20260116.dist-info/RECORD
