Metadata-Version: 2.4
Name: mcp-server-sqlite3
Version: 20260116
Summary: SQLite3 tools for MCP
Requires-Python: >=3.13
Requires-Dist: mcp[cli]>=1.25.0
